{
  "targets": [
    {
      "settore": "ristoranti",
      "citta": "Milano"
    },
    {
      "settore": "pizzerie",
      "citta": "Milano"
    },
    {
      "settore": "bar",
      "citta": "Milano"
    },
    {
      "settore": "pasticcerie",
      "citta": "Milano"
    },
    {
      "settore": "gelaterie",
      "citta": "Milano"
    },
    {
      "settore": "enoteche",
      "citta": "Milano"
    },
    {
      "settore": "catering",
      "citta": "Milano"
    },
    {
      "settore": "food truck",
      "citta": "Milano"
    },
    {
      "settore": "dentisti",
      "citta": "Milano"
    },
    {
      "settore": "medici estetici",
      "citta": "Milano"
    },
    {
      "settore": "fisioterapisti",
      "citta": "Milano"
    },
    {
      "settore": "nutrizionisti",
      "citta": "Milano"
    },
    {
      "settore": "psicologi",
      "citta": "Milano"
    },
    {
      "settore": "veterinari",
      "citta": "Milano"
    },
    {
      "settore": "farmacie",
      "citta": "Milano"
    },
    {
      "settore": "palestre",
      "citta": "Milano"
    },
    {
      "settore": "centri benessere",
      "citta": "Milano"
    },
    {
      "settore": "parrucchieri",
      "citta": "Milano"
    },
    {
      "settore": "centri estetici",
      "citta": "Milano"
    },
    {
      "settore": "barbieri",
      "citta": "Milano"
    },
    {
      "settore": "nail salon",
      "citta": "Milano"
    },
    {
      "settore": "hotel",
      "citta": "Milano"
    },
    {
      "settore": "B&B",
      "citta": "Milano"
    },
    {
      "settore": "negozi abbigliamento",
      "citta": "Milano"
    },
    {
      "settore": "gioiellerie",
      "citta": "Milano"
    },
    {
      "settore": "ottica",
      "citta": "Milano"
    },
    {
      "settore": "arredamento",
      "citta": "Milano"
    },
    {
      "settore": "fiorai",
      "citta": "Milano"
    },
    {
      "settore": "concessionarie auto",
      "citta": "Milano"
    },
    {
      "settore": "officine meccaniche",
      "citta": "Milano"
    },
    {
      "settore": "carrozzerie",
      "citta": "Milano"
    },
    {
      "settore": "noleggio auto",
      "citta": "Milano"
    },
    {
      "settore": "corsi di lingua",
      "citta": "Milano"
    },
    {
      "settore": "scuole di danza",
      "citta": "Milano"
    },
    {
      "settore": "imprese edili",
      "citta": "Milano"
    },
    {
      "settore": "interior design",
      "citta": "Milano"
    },
    {
      "settore": "ristoranti",
      "citta": "Bergamo"
    },
    {
      "settore": "dentisti",
      "citta": "Bergamo"
    },
    {
      "settore": "palestre",
      "citta": "Bergamo"
    },
    {
      "settore": "parrucchieri",
      "citta": "Bergamo"
    },
    {
      "settore": "hotel",
      "citta": "Bergamo"
    },
    {
      "settore": "bar",
      "citta": "Bergamo"
    },
    {
      "settore": "ristoranti",
      "citta": "Brescia"
    },
    {
      "settore": "dentisti",
      "citta": "Brescia"
    },
    {
      "settore": "palestre",
      "citta": "Brescia"
    },
    {
      "settore": "parrucchieri",
      "citta": "Brescia"
    },
    {
      "settore": "hotel",
      "citta": "Brescia"
    },
    {
      "settore": "bar",
      "citta": "Brescia"
    },
    {
      "settore": "ristoranti",
      "citta": "Monza"
    },
    {
      "settore": "dentisti",
      "citta": "Monza"
    },
    {
      "settore": "palestre",
      "citta": "Monza"
    },
    {
      "settore": "ristoranti",
      "citta": "Como"
    },
    {
      "settore": "hotel",
      "citta": "Como"
    },
    {
      "settore": "dentisti",
      "citta": "Como"
    },
    {
      "settore": "ristoranti",
      "citta": "Varese"
    },
    {
      "settore": "dentisti",
      "citta": "Varese"
    },
    {
      "settore": "hotel",
      "citta": "Varese"
    },
    {
      "settore": "ristoranti",
      "citta": "Pavia"
    },
    {
      "settore": "dentisti",
      "citta": "Pavia"
    },
    {
      "settore": "ristoranti",
      "citta": "Cremona"
    },
    {
      "settore": "dentisti",
      "citta": "Cremona"
    },
    {
      "settore": "ristoranti",
      "citta": "Mantova"
    },
    {
      "settore": "hotel",
      "citta": "Mantova"
    },
    {
      "settore": "ristoranti",
      "citta": "Lecco"
    },
    {
      "settore": "ristoranti",
      "citta": "Lodi"
    },
    {
      "settore": "ristoranti",
      "citta": "Sondrio"
    }
  ],
  "current_index": 7
}